{
  "pivot_rows": [
    {
      "pivot": 12,
      "row": {
        "12": 1,
        "96": -1
      }
    },
    {
      "pivot": 13,
      "row": {
        "102": -1,
        "114": "1/2",
        "123": -1,
        "13": 1,
        "57": "1/2",
        "59": "1/2",
        "88": "-1/2"
      }
    },
    {
      "pivot": 14,
      "row": {
        "103": -1,
        "115": -2,
        "117": 2,
        "124": -2,
        "129": -2,
        "138": "1/2",
        "14": 1,
        "147": -1,
        "58": 2,
        "60": 2,
        "62": 1,
        "89": "-1/2"
      }
    },
    {
      "pivot": 15,
      "row": {
        "15": 1,
        "57": -1
      }
    },
    {
      "pivot": 16,
      "row": {
        "16": 1,
        "58": -1
      }
    },
    {
      "pivot": 17,
      "row": {
        "116": -1,
        "130": -2,
        "139": -1,
        "141": 2,
        "148": -1,
        "153": -1,
        "17": 1,
        "61": 1,
        "63": 2
      }
    },
    {
      "pivot": 18,
      "row": {
        "18": 1,
        "59": -1
      }
    },
    {
      "pivot": 19,
      "row": {
        "103": "1/2",
        "138": "-1/4",
        "19": 1,
        "60": -1,
        "62": "-1/2",
        "89": "1/4"
      }
    },
    {
      "pivot": 20,
      "row": {
        "116": 1,
        "130": 2,
        "141": -1,
        "20": 1,
        "61": -1,
        "63": -2
      }
    },
    {
      "pivot": 21,
      "row": {
        "21": 1,
        "59": -1
      }
    },
    {
      "pivot": 22,
      "row": {
        "22": 1,
        "60": -1
      }
    },
    {
      "pivot": 23,
      "row": {
        "23": 1,
        "61": -1
      }
    },
    {
      "pivot": 24,
      "row": {
        "24": 1,
        "62": -1
      }
    },
    {
      "pivot": 25,
      "row": {
        "25": 1,
        "63": -1
      }
    },
    {
      "pivot": 26,
      "row": {
        "140": "-1/2",
        "144": "1/2",
        "154": -1,
        "26": 1
      }
    },
    {
      "pivot": 27,
      "row": {
        "114": "-1/2",
        "123": -1,
        "27": 1,
        "88": "1/2"
      }
    },
    {
      "pivot": 28,
      "row": {
        "115": "1/2",
        "117": "-1/2",
        "124": "-1/2",
        "125": -1,
        "129": "-1/2",
        "28": 1,
        "64": "1/2",
        "66": "1/2"
      }
    },
    {
      "pivot": 29,
      "row": {
        "116": "-1/2",
        "130": -1,
        "131": -4,
        "139": 1,
        "141": "-1/2",
        "149": -1,
        "29": 1,
        "65": 2,
        "67": 2,
        "69": 1
      }
    },
    {
      "pivot": 30,
      "row": {
        "30": 1,
        "64": -1
      }
    },
    {
      "pivot": 31,
      "row": {
        "31": 1,
        "65": -1
      }
    },
    {
      "pivot": 32,
      "row": {
        "119": -1,
        "132": -2,
        "142": 1,
        "150": -1,
        "155": -1,
        "32": 1,
        "68": 1,
        "70": 2
      }
    },
    {
      "pivot": 33,
      "row": {
        "33": 1,
        "66": -1
      }
    },
    {
      "pivot": 34,
      "row": {
        "116": "1/4",
        "130": "1/2",
        "139": "-1/4",
        "34": 1,
        "67": -1,
        "69": "-1/2"
      }
    },
    {
      "pivot": 35,
      "row": {
        "119": 1,
        "132": 2,
        "142": -1,
        "35": 1,
        "68": -1,
        "70": -2
      }
    },
    {
      "pivot": 36,
      "row": {
        "36": 1,
        "66": -1
      }
    },
    {
      "pivot": 37,
      "row": {
        "37": 1,
        "67": -1
      }
    },
    {
      "pivot": 38,
      "row": {
        "38": 1,
        "68": -1
      }
    },
    {
      "pivot": 39,
      "row": {
        "39": 1,
        "69": -1
      }
    },
    {
      "pivot": 40,
      "row": {
        "40": 1,
        "70": -1
      }
    },
    {
      "pivot": 41,
      "row": {
        "143": "-1/2",
        "145": "1/2",
        "156": -1,
        "41": 1
      }
    },
    {
      "pivot": 42,
      "row": {
        "138": "-1/2",
        "147": -1,
        "42": 1,
        "89": "1/2"
      }
    },
    {
      "pivot": 43,
      "row": {
        "116": 1,
        "139": "-1/2",
        "141": "-1/2",
        "148": "-1/2",
        "149": -1,
        "153": "-1/2",
        "43": 1,
        "71": "1/2",
        "73": "1/2"
      }
    },
    {
      "pivot": 44,
      "row": {
        "119": 2,
        "140": "1/2",
        "142": -2,
        "144": "-1/2",
        "150": -2,
        "151": -1,
        "154": -1,
        "155": -2,
        "44": 1,
        "72": 2,
        "74": 2,
        "76": 1
      }
    },
    {
      "pivot": 45,
      "row": {
        "45": 1,
        "71": -1
      }
    },
    {
      "pivot": 46,
      "row": {
        "46": 1,
        "72": -1
      }
    },
    {
      "pivot": 47,
      "row": {
        "143": 1,
        "145": -1,
        "156": -2,
        "157": -2,
        "47": 1,
        "75": 1,
        "77": 2
      }
    },
    {
      "pivot": 48,
      "row": {
        "48": 1,
        "73": -1
      }
    },
    {
      "pivot": 49,
      "row": {
        "154": "1/2",
        "49": 1,
        "74": -1,
        "76": "-1/2"
      }
    },
    {
      "pivot": 50,
      "row": {
        "156": 2,
        "50": 1,
        "75": -1,
        "77": -2
      }
    },
    {
      "pivot": 51,
      "row": {
        "51": 1,
        "73": -1
      }
    },
    {
      "pivot": 52,
      "row": {
        "52": 1,
        "74": -1
      }
    },
    {
      "pivot": 53,
      "row": {
        "53": 1,
        "75": -1
      }
    },
    {
      "pivot": 54,
      "row": {
        "54": 1,
        "76": -1
      }
    },
    {
      "pivot": 55,
      "row": {
        "55": 1,
        "77": -1
      }
    },
    {
      "pivot": 56,
      "row": {
        "158": -1,
        "56": 1
      }
    },
    {
      "pivot": 78,
      "row": {
        "78": 1,
        "87": -1
      }
    },
    {
      "pivot": 79,
      "row": {
        "79": 1,
        "88": -1
      }
    },
    {
      "pivot": 80,
      "row": {
        "80": 1,
        "89": -1
      }
    },
    {
      "pivot": 81,
      "row": {
        "114": -1,
        "81": 1
      }
    },
    {
      "pivot": 82,
      "row": {
        "115": -1,
        "82": 1
      }
    },
    {
      "pivot": 83,
      "row": {
        "116": -1,
        "83": 1
      }
    },
    {
      "pivot": 84,
      "row": {
        "138": -1,
        "84": 1
      }
    },
    {
      "pivot": 85,
      "row": {
        "139": -1,
        "85": 1
      }
    },
    {
      "pivot": 86,
      "row": {
        "140": -1,
        "86": 1
      }
    },
    {
      "pivot": 90,
      "row": {
        "114": -1,
        "90": 1
      }
    },
    {
      "pivot": 91,
      "row": {
        "115": -1,
        "91": 1
      }
    },
    {
      "pivot": 92,
      "row": {
        "116": -1,
        "92": 1
      }
    },
    {
      "pivot": 93,
      "row": {
        "138": -1,
        "93": 1
      }
    },
    {
      "pivot": 94,
      "row": {
        "139": -1,
        "94": 1
      }
    },
    {
      "pivot": 95,
      "row": {
        "140": -1,
        "95": 1
      }
    },
    {
      "pivot": 97,
      "row": {
        "102": -1,
        "97": 1
      }
    },
    {
      "pivot": 98,
      "row": {
        "123": -1,
        "98": 1
      }
    },
    {
      "pivot": 99,
      "row": {
        "129": -1,
        "99": 1
      }
    },
    {
      "pivot": 100,
      "row": {
        "100": 1,
        "147": -1
      }
    },
    {
      "pivot": 101,
      "row": {
        "101": 1,
        "153": -1
      }
    },
    {
      "pivot": 104,
      "row": {
        "104": 1,
        "124": -1
      }
    },
    {
      "pivot": 105,
      "row": {
        "105": 1,
        "130": -1
      }
    },
    {
      "pivot": 106,
      "row": {
        "106": 1,
        "148": -1
      }
    },
    {
      "pivot": 107,
      "row": {
        "107": 1,
        "154": -1
      }
    },
    {
      "pivot": 108,
      "row": {
        "108": 1,
        "117": -1
      }
    },
    {
      "pivot": 109,
      "row": {
        "109": 1,
        "118": -1
      }
    },
    {
      "pivot": 110,
      "row": {
        "110": 1,
        "119": -1
      }
    },
    {
      "pivot": 111,
      "row": {
        "111": 1,
        "141": -1
      }
    },
    {
      "pivot": 112,
      "row": {
        "112": 1,
        "142": -1
      }
    },
    {
      "pivot": 113,
      "row": {
        "113": 1,
        "143": -1
      }
    },
    {
      "pivot": 120,
      "row": {
        "120": 1,
        "141": -1
      }
    },
    {
      "pivot": 121,
      "row": {
        "121": 1,
        "142": -1
      }
    },
    {
      "pivot": 122,
      "row": {
        "122": 1,
        "143": -1
      }
    },
    {
      "pivot": 126,
      "row": {
        "126": 1,
        "131": -1
      }
    },
    {
      "pivot": 127,
      "row": {
        "127": 1,
        "149": -1
      }
    },
    {
      "pivot": 128,
      "row": {
        "128": 1,
        "155": -1
      }
    },
    {
      "pivot": 133,
      "row": {
        "133": 1,
        "150": -1
      }
    },
    {
      "pivot": 134,
      "row": {
        "134": 1,
        "156": -1
      }
    },
    {
      "pivot": 135,
      "row": {
        "135": 1,
        "144": -1
      }
    },
    {
      "pivot": 136,
      "row": {
        "136": 1,
        "145": -1
      }
    },
    {
      "pivot": 137,
      "row": {
        "137": 1,
        "146": -1
      }
    },
    {
      "pivot": 152,
      "row": {
        "152": 1,
        "157": -1
      }
    }
  ],
  "rank": 87
}
